twiplies/__init__.py
twiplies/_modidx.py
twiplies/core.py
twiplies/io/__init__.py
twiplies/io/build_dataframe.py
twiplies-0.0.4.dist-info/LICENSE
twiplies-0.0.4.dist-info/METADATA
twiplies-0.0.4.dist-info/WHEEL
twiplies-0.0.4.dist-info/entry_points.txt
twiplies-0.0.4.dist-info/top_level.txt
twiplies-0.0.4.dist-info/RECORD
