Metadata-Version: 2.1
Name: twiplies
Version: 0.0.4
Summary: Get tweets replies from a user account
Home-page: https://github.com/joaopcnogueira/twiplies/
Author: João Nogueira
Author-email: joao.nogueira@datarisk.io
License: Apache Software License 2.0
Keywords: nbdev
Platform: UNKNOWN
Classifier: Development Status :: 3 - Alpha
Classifier: Intended Audience :: Developers
Classifier: Natural Language :: English
Classifier: Programming Language :: Python :: 3.8
Classifier: Programming Language :: Python :: 3.9
Classifier: Programming Language :: Python :: 3.10
Classifier: License :: OSI Approved :: Apache Software License
Requires-Python: >=3.8
License-File: LICENSE
Requires-Dist: fastcore
Requires-Dist: pandas
Requires-Dist: tweepy
Provides-Extra: dev
Requires-Dist: python-dotenv ; extra == 'dev'
Requires-Dist: jupyter ; extra == 'dev'
